{
  "annotations": {
    "list": []
  },
  "editable": true,
  "fiscalYearStartMonth": 0,
  "graphTooltip": 0,
  "id": null,
  "links": [],
  "liveNow": false,
  "panels": [
    {
      "datasource": {
        "type": "prometheus",
        "uid": "prometheus"
      },
      "fieldConfig": {
        "defaults": {
          "color": {
            "mode": "palette-classic"
          },
          "mappings": [],
          "thresholds": {
            "mode": "absolute",
            "steps": [
              {"color": "green", "value": null}
            ]
          }
        }
      },
      "gridPos": {"h": 4, "w": 6, "x": 0, "y": 0},
      "id": 1,
      "options": {
        "colorMode": "value",
        "graphMode": "area",
        "justifyMode": "auto",
        "orientation": "auto",
        "reduceOptions": {
          "calcs": ["lastNotNull"],
          "fields": "",
          "values": false
        },
        "textMode": "auto"
      },
      "title": "Connector Status",
      "type": "stat",
      "targets": [
        {
          "expr": "count(kafka_connect_connector_state{state=\"running\"})",
          "legendFormat": "Running",
          "refId": "A"
        }
      ]
    },
    {
      "datasource": {
        "type": "prometheus",
        "uid": "prometheus"
      },
      "fieldConfig": {
        "defaults": {
          "color": {
            "mode": "palette-classic"
          },
          "custom": {
            "axisBorderShow": false,
            "axisCenteredZero": false,
            "axisColorMode": "text",
            "axisLabel": "",
            "axisPlacement": "auto",
            "barAlignment": 0,
            "drawStyle": "line",
            "fillOpacity": 20,
            "gradientMode": "none",
            "hideFrom": {"legend": false, "tooltip": false, "viz": false},
            "insertNulls": false,
            "lineInterpolation": "linear",
            "lineWidth": 2,
            "pointSize": 5,
            "scaleDistribution": {"type": "linear"},
            "showPoints": "auto",
            "spanNulls": false,
            "stacking": {"group": "A", "mode": "none"},
            "thresholdsStyle": {"mode": "off"}
          },
          "mappings": [],
          "thresholds": {
            "mode": "absolute",
            "steps": [{"color": "green", "value": null}]
          },
          "unit": "ops"
        }
      },
      "gridPos": {"h": 8, "w": 12, "x": 6, "y": 0},
      "id": 2,
      "options": {
        "legend": {"calcs": [], "displayMode": "list", "placement": "bottom", "showLegend": true},
        "tooltip": {"mode": "single", "sort": "none"}
      },
      "title": "Message Throughput",
      "type": "timeseries",
      "targets": [
        {
          "expr": "rate(kafka_connect_connector_task_metrics_messages_consumed_total[5m])",
          "legendFormat": "Messages Consumed/s",
          "refId": "A"
        },
        {
          "expr": "rate(kafka_connect_connector_task_metrics_messages_produced_total[5m])",
          "legendFormat": "Messages Produced/s",
          "refId": "B"
        }
      ]
    },
    {
      "datasource": {
        "type": "prometheus",
        "uid": "prometheus"
      },
      "fieldConfig": {
        "defaults": {
          "color": {
            "mode": "palette-classic"
          },
          "custom": {
            "axisBorderShow": false,
            "axisCenteredZero": false,
            "axisColorMode": "text",
            "axisLabel": "",
            "axisPlacement": "auto",
            "barAlignment": 0,
            "drawStyle": "line",
            "fillOpacity": 20,
            "gradientMode": "none",
            "hideFrom": {"legend": false, "tooltip": false, "viz": false},
            "insertNulls": false,
            "lineInterpolation": "linear",
            "lineWidth": 2,
            "pointSize": 5,
            "scaleDistribution": {"type": "linear"},
            "showPoints": "auto",
            "spanNulls": false,
            "stacking": {"group": "A", "mode": "none"},
            "thresholdsStyle": {"mode": "off"}
          },
          "mappings": [],
          "thresholds": {
            "mode": "absolute",
            "steps": [{"color": "green", "value": null}]
          }
        }
      },
      "gridPos": {"h": 8, "w": 12, "x": 0, "y": 8},
      "id": 3,
      "options": {
        "legend": {"calcs": [], "displayMode": "list", "placement": "bottom", "showLegend": true},
        "tooltip": {"mode": "single", "sort": "none"}
      },
      "title": "Connector Task Status",
      "type": "timeseries",
      "targets": [
        {
          "expr": "kafka_connect_connector_task_metrics_task_status{state=\"running\"}",
          "legendFormat": "{{connector}} Task {{task_id}} Running",
          "refId": "A"
        }
      ]
    },
    {
      "datasource": {
        "type": "prometheus",
        "uid": "prometheus"
      },
      "fieldConfig": {
        "defaults": {
          "color": {
            "mode": "palette-classic"
          },
          "custom": {
            "axisBorderShow": false,
            "axisCenteredZero": false,
            "axisColorMode": "text",
            "axisLabel": "",
            "axisPlacement": "auto",
            "barAlignment": 0,
            "drawStyle": "line",
            "fillOpacity": 20,
            "gradientMode": "none",
            "hideFrom": {"legend": false, "tooltip": false, "viz": false},
            "insertNulls": false,
            "lineInterpolation": "linear",
            "lineWidth": 2,
            "pointSize": 5,
            "scaleDistribution": {"type": "linear"},
            "showPoints": "auto",
            "spanNulls": false,
            "stacking": {"group": "A", "mode": "none"},
            "thresholdsStyle": {"mode": "off"}
          },
          "mappings": [],
          "thresholds": {
            "mode": "absolute",
            "steps": [{"color": "green", "value": null}]
          }
        }
      },
      "gridPos": {"h": 8, "w": 12, "x": 12, "y": 8},
      "id": 4,
      "options": {
        "legend": {"calcs": [], "displayMode": "list", "placement": "bottom", "showLegend": true},
        "tooltip": {"mode": "single", "sort": "none"}
      },
      "title": "Offset Lag",
      "type": "timeseries",
      "targets": [
        {
          "expr": "kafka_connect_connector_task_metricsConsumer_fetch_manager_records_lag_max",
          "legendFormat": "{{topic}} Lag",
          "refId": "A"
        }
      ]
    },
    {
      "datasource": {
        "type": "prometheus",
        "uid": "prometheus"
      },
      "fieldConfig": {
        "defaults": {
          "color": {
            "mode": "palette-classic"
          },
          "custom": {
            "axisBorderShow": false,
            "axisCenteredZero": false,
            "axisColorMode": "text",
            "axisLabel": "",
            "axisPlacement": "auto",
            "barAlignment": 0,
            "drawStyle": "line",
            "fillOpacity": 20,
            "gradientMode": "none",
            "hideFrom": {"legend": false, "tooltip": false, "viz": false},
            "insertNulls": false,
            "lineInterpolation": "linear",
            "lineWidth": 2,
            "pointSize": 5,
            "scaleDistribution": {"type": "linear"},
            "showPoints": "auto",
            "spanNulls": false,
            "stacking": {"group": "A", "mode": "none"},
            "thresholdsStyle": {"mode": "off"}
          },
          "mappings": [],
          "thresholds": {
            "mode": "absolute",
            "steps": [{"color": "green", "value": null}]
          }
        }
      },
      "gridPos": {"h": 8, "w": 12, "x": 0, "y": 16},
      "id": 5,
      "options": {
        "legend": {"calcs": [], "displayMode": "list", "placement": "bottom", "showLegend": true},
        "tooltip": {"mode": "single", "sort": "none"}
      },
      "title": "Debezium Metrics - Batch Size",
      "type": "timeseries",
      "targets": [
        {
          "expr": "rate(debezium_changemask_data_collections_BufferedChangeRecordCount[5m])",
          "legendFormat": "Buffered Records",
          "refId": "A"
        }
      ]
    },
    {
      "datasource": {
        "type": "prometheus",
        "uid": "prometheus"
      },
      "fieldConfig": {
        "defaults": {
          "color": {
            "mode": "palette-classic"
          },
          "custom": {
            "axisBorderShow": false,
            "axisCenteredZero": false,
            "axisColorMode": "text",
            "axisLabel": "",
            "axisPlacement": "auto",
            "barAlignment": 0,
            "drawStyle": "line",
            "fillOpacity": 20,
            "gradientMode": "none",
            "hideFrom": {"legend": false, "tooltip": false, "viz": false},
            "insertNulls": false,
            "lineInterpolation": "linear",
            "lineWidth": 2,
            "pointSize": 5,
            "scaleDistribution": {"type": "linear"},
            "showPoints": "auto",
            "spanNulls": false,
            "stacking": {"group": "A", "mode": "none"},
            "thresholdsStyle": {"mode": "off"}
          },
          "mappings": [],
          "thresholds": {
            "mode": "absolute",
            "steps": [{"color": "green", "value": null}]
          }
        }
      },
      "gridPos": {"h": 8, "w": 12, "x": 12, "y": 16},
      "id": 6,
      "options": {
        "legend": {"calcs": [], "displayMode": "list", "placement": "bottom", "showLegend": true},
        "tooltip": {"mode": "single", "sort": "none"}
      },
      "title": "Debezium Metrics - Events",
      "type": "timeseries",
      "targets": [
        {
          "expr": "rate(debezium_changes_events_total[5m])",
          "legendFormat": "CDC Events/s",
          "refId": "A"
        }
      ]
    }
  ],
  "refresh": "5s",
  "schemaVersion": 38,
  "tags": ["kafka", "debezium", "cdc"],
  "templating": {
    "list": []
  },
  "time": {
    "from": "now-15m",
    "to": "now"
  },
  "timepicker": {},
  "timezone": "",
  "title": "Kafka Connect CDC Monitoring",
  "uid": "kafka-cdc-dashboard",
  "version": 1,
  "weekStart": ""
}
